textqueue/__init__.py
textqueue/main.py
textqueue/py.typed
textqueue-1.1.dist-info/METADATA
textqueue-1.1.dist-info/WHEEL
textqueue-1.1.dist-info/top_level.txt
textqueue-1.1.dist-info/RECORD
