Metadata-Version: 2.1
Name: textqueue
Version: 1.1
Summary: A text-based queue tool
Author-email: Asher Glick <aglick@aglick.com>
Classifier: Programming Language :: Python :: 3
Classifier: License :: OSI Approved :: BSD License
Classifier: Operating System :: OS Independent
